{
  "songli_1":{"appVersion":"1.0.9", "os":"android", "ticket":"6a76415326ea7b0595af552d17056be5", "netType":"2", "channel":"bells", "appCode":"39", "type":"2", "deviceId":"9be788ab-6557-4e48-9f5f-ab4f581b149e", "giftId":"317", "uid":"390", "osVersion":"9", "appid":"xchat", "giftNum":"1", "imei":"869120044437479", "model":"MI+CC+9", "targetUid":"388", "ispType":"2"},
  "songli_2":{"appVersion":"1.0.9", "os":"android", "ticket":"6a76415326ea7b0595af552d17056be5", "netType":"2", "channel":"bells", "appCode":"39", "type":"2", "deviceId":"9be788ab-6557-4e48-9f5f-ab4f581b149e", "giftId":"317", "uid":"390", "osVersion":"9", "appid":"xchat", "giftNum":"1", "imei":"869120044437479", "model":"MI+CC+9", "targetUid":"", "ispType":"2"},
  "songli_3":{"appVersion":"1.0.9", "os":"android", "ticket":"6a76415326ea7b0595af552d17056be5", "netType":"2", "channel":"bells", "appCode":"39", "type":"2", "deviceId":"9be788ab-6557-4e48-9f5f-ab4f581b149e", "giftId":"317", "uid":"390", "osVersion":"9", "appid":"xchat", "giftNum":"1", "imei":"869120044437479", "model":"MI+CC+9", "targetUid":"", "ispType":"2"},
  "songli_4":{"appVersion":"1.0.9", "os":"android", "ticket":"6a76415326ea7b0595af552d17056be5", "netType":"2", "channel":"bells", "appCode":"39", "type":"2", "deviceId":"9be788ab-6557-4e48-9f5f-ab4f581b149e", "giftId":"317", "uid":"390", "osVersion":"9", "appid":"xchat", "giftNum":"1", "imei":"869120044437479", "model":"MI+CC+9", "targetUid":"", "ispType":"2"},
  "songli_5":{"appVersion":"1.0.9", "os":"android", "ticket":"", "netType":"2", "channel":"bells", "appCode":"39", "type":"2", "deviceId":"9be788ab-6557-4e48-9f5f-ab4f581b149e", "giftId":"317", "uid":"390", "osVersion":"9", "appid":"xchat", "giftNum":"1", "imei":"869120044437479", "model":"MI+CC+9", "targetUid":"388", "ispType":"2"},
  "songli_6":{"appVersion":"1.0.9", "os":"android", "ticket":"6a76415326ea7b0595af552d17056be5", "netType":"2", "channel":"bells", "appCode":"39", "type":"2", "deviceId":"9be788ab-6557-4e48-9f5f-ab4f581b149e", "giftId":"677327357138521", "uid":"390", "osVersion":"9", "appid":"xchat", "giftNum":"1", "imei":"869120044437479", "model":"MI+CC+9", "targetUid":"388", "ispType":"2"},
  "songli_7":{"appVersion":"1.0.9", "os":"android", "ticket":"11111111111111", "netType":"2", "channel":"bells", "appCode":"39", "type":"2", "deviceId":"9be788ab-6557-4e48-9f5f-ab4f581b149e", "giftId":"317", "uid":"390", "osVersion":"9", "appid":"xchat", "giftNum":"1", "imei":"869120044437479", "model":"MI+CC+9", "targetUid":"388", "ispType":"2"},
  "login_1":{"user": "13045899811", "psw": "123456"},
  "login_2": {"user": "", "psw": "123456", "login_type": "0"},
  "login_3": {"user": "13045899811", "psw": "", "login_type": "0"},
  "login_4": {"useraaa": "13045899811", "psw": "", "login_type": "0"},
  "login_5": {"psw": "", "login_type": "0"},
  "login_6": {"user": "13045899811", "psw": "", "login_type": "0","aaa": "wewe"},
  "login_7":{"user": "誓师大会。。，", "psw": "123456", "login_type": "0"},
  "login_8":{"user": "13045899811", "psw": "涣发大号？，。", "login_type": "0"},
  "login_9":{"user": "1304589981167", "psw": "123456", "login_type": "0"},
  "login_10":{"user": "13045899811", "psw": "1234561234567890", "login_type": "0"},
  "login_11":{"user": "13045", "psw": "123456", "login_type": "0"},
  "login_12":{"user": "13045899811", "psw": "123", "login_type": "0"},
  "huoqu_1":{},
  "huoqu_2":{},
  "huoqu_3":{},
  "huoqu_4":{},
  "huoqu_5":{},
  "huoqu_6":{},
  "huoqu_7":{},
  "huoqu_8":{},
  "huoqu_9":{},
  "huoqu_10":{},
  "huoqu_11":{},
  "huoqu_12":{},
  "huoqu_13":{},
  "huoqu_14":{},
  "huoqu_15":{},
  "huoqu_16":{},
  "huoqu_17":{},
  "huoqu_18":{},
  "huoqu_19":{},
  "huoqu_20":{},
  "huoqu_21":{},
  "huoqu_22":{},
  "huoqu_23":{},
  "huoqu_24":{},
  "huoqu_25":{},
  "huoqu_26":{},
  "huoqu_27":{},
  "huoqu_28":{},
  "huoqu_29":{},
  "huoqu_30":{},
  "huoqu_31":{},
  "huoqu_32":{},
  "huoqu_33":{},
  "huoqu_34":{},
  "huoqu_35":{},
  "huoqu_36":{},
  "huoqu_37":{},
  "huoqu_38":{},
  "huoqu_39":{},
  "huoqu_40":{},
  "huoqu_41":{},
  "huoqu_42":{},
  "huoqu_43":{},
  "huoqu_44":{},
  "huoqu_45":{},
  "huoqu_46":{},
  "huoqu_47":{},
  "huoqu_48":{},
  "huoqu_49":{},
  "huoqu_50":{},
  "huoqu_51":{},
  "huoqu_52":{},
  "huoqu_53":{},
  "huoqu_54":{},
  "huoqu_55":{},
  "huoqu_56":{},
  "huoqu_57":{},
  "huoqu_58":{},
  "huoqu_59":{},
  "huoqu_60":{},
  "huoqu_61":{},
  "huoqu_62":{},
  "huoqu_63":{},
  "huoqu_64":{},
  "huoqu_65":{},
  "huoqu_66":{},
  "huoqu_67":{},
  "huoqu_68":{},
  "huoqu_69":{},
  "huoqu_70":{},
  "huoqu_71":{},
  "huoqu_72":{},
  "huoqu_73":{},
  "huoqu_74":{},
  "huoqu_75":{},
  "huoqu_76":{},
  "huoqu_77":{},
  "huoqu_78":{},
  "huoqu_79":{},
  "huoqu_80":{},
  "huoqu_81":{},
  "huoqu_82":{},
  "huoqu_83":{},
  "huoqu_84":{},
  "huoqu_85":{},
  "huoqu_86":{},
  "huoqu_87":{},
  "huoqu_88":{},
  "huoqu_89":{},
  "huoqu_90":{},
  "huoqu_91":{},
  "huoqu_92":{},
  "huoqu_93":{},
  "huoqu_94":{},
  "huoqu_95":{},
  "huoqu_96":{},
  "huoqu_97":{},
  "huoqu_98":{},
  "huoqu_99":{},
  "huoqu_100":{},
  "huoqu_101":{},
  "huoqu_102":{},
  "huoqu_103":{},
  "huoqu_104":{},
  "huoqu_105":{},
  "huoqu_106":{},
  "huoqu_107":{},
  "huoqu_108":{},
  "huoqu_109":{},
  "huoqu_110":{},
  "huoqu_111":{},
  "huoqu_112":{},
  "huoqu_113":{},
  "huoqu_114":{},
  "huoqu_115":{},
  "huoqu_116":{},
  "huoqu_117":{},
  "huoqu_118":{},
  "huoqu_119":{},
  "huoqu_120":{},
  "huoqu_121":{},
  "huoqu_122":{},
  "huoqu_123":{},
  "huoqu_124":{},
  "huoqu_125":{},
  "huoqu_126":{},
  "huoqu_127":{},
  "huoqu_128":{},
  "huoqu_129":{},
  "huoqu_130":{},
  "huoqu_131":{},
  "huoqu_132":{},
  "huoqu_133":{},
  "huoqu_134":{},
  "huoqu_135":{},
  "huoqu_136":{},
  "huoqu_137":{},
  "huoqu_138":{},
  "huoqu_139":{},
  "huoqu_140":{},
  "huoqu_141":{},
  "huoqu_142":{},
  "huoqu_143":{},
  "huoqu_144":{},
  "huoqu_145":{},
  "huoqu_146":{},
  "huoqu_147":{},
  "huoqu_148":{},
  "huoqu_149":{},
  "huoqu_150":{},
  "huoqu_151":{},
  "huoqu_152":{},
  "huoqu_153":{},
  "huoqu_154":{},
  "huoqu_155":{},
  "huoqu_156":{},
  "huoqu_157":{},
  "huoqu_158":{},
  "huoqu_159":{},
  "huoqu_160":{},
  "huoqu_161":{},
  "huoqu_162":{},
  "huoqu_163":{},
  "huoqu_164":{},
  "huoqu_165":{},
  "huoqu_166":{},
  "huoqu_167":{},
  "huoqu_168":{},
  "huoqu_169":{},
  "huoqu_170":{},
  "huoqu_171":{},
  "huoqu_172":{},
  "huoqu_173":{},
  "huoqu_174":{},
  "huoqu_175":{},
  "huoqu_176":{},
  "huoqu_177":{},
  "huoqu_178":{},
  "huoqu_179":{},
  "huoqu_180":{},
  "huoqu_181":{},
  "huoqu_182":{},
  "huoqu_183":{},
  "huoqu_184":{},
  "huoqu_185":{},
  "huoqu_186":{},
  "huoqu_187":{},
  "huoqu_188":{},
  "huoqu_189":{},
  "huoqu_190":{},
  "huoqu_191":{},
  "huoqu_192":{},
  "huoqu_193":{},
  "huoqu_194":{},
  "huoqu_195":{},
  "huoqu_196":{},
  "huoqu_197":{},
  "huoqu_198":{},
  "huoqu_199":{},
  "huoqu_200":{},
  "huoqu_201":{},
  "huoqu_202":{},
  "huoqu_203":{},
  "huoqu_204":{},
  "huoqu_205":{},
  "huoqu_206":{},
  "huoqu_207":{},
  "huoqu_208":{},
  "huoqu_209":{},
  "huoqu_210":{},
  "huoqu_211":{},
  "huoqu_212":{},
  "huoqu_213":{},
  "huoqu_214":{},
  "huoqu_215":{},
  "huoqu_216":{},
  "huoqu_217":{},
  "huoqu_218":{},
  "huoqu_219":{},
  "huoqu_220":{},
  "huoqu_221":{},
  "huoqu_222":{},
  "huoqu_223":{},
  "huoqu_224":{},
  "huoqu_225":{},
  "huoqu_226":{},
  "huoqu_227":{},
  "huoqu_228":{},
  "huoqu_229":{},
  "huoqu_230":{},
  "huoqu_231":{},
  "huoqu_232":{},
  "huoqu_233":{},
  "huoqu_234":{},
  "huoqu_235":{},
  "huoqu_236":{},
  "huoqu_237":{},
  "huoqu_238":{},
  "huoqu_239":{},
  "huoqu_240":{},
  "huoqu_241":{},
  "huoqu_242":{},
  "huoqu_243":{},
  "huoqu_244":{},
  "huoqu_245":{},
  "huoqu_246":{},
  "huoqu_247":{},
  "huoqu_248":{},
  "huoqu_249":{},
  "huoqu_250":{},
  "huoqu_251":{},
  "huoqu_252":{},
  "huoqu_253":{},
  "huoqu_254":{},
  "huoqu_255":{},
  "huoqu_256":{},
  "huoqu_257":{},
  "huoqu_258":{},
  "huoqu_259":{},
  "huoqu_260":{},
  "huoqu_261":{},
  "huoqu_262":{},
  "huoqu_263":{},
  "huoqu_264":{},
  "huoqu_265":{},
  "huoqu_266":{},
  "huoqu_267":{},
  "huoqu_268":{},
  "huoqu_269":{},
  "huoqu_270":{},
  "huoqu_271":{},
  "huoqu_272":{},
  "huoqu_273":{},
  "huoqu_274":{},
  "huoqu_275":{},
  "huoqu_276":{},
  "huoqu_277":{},
  "huoqu_278":{},
  "huoqu_279":{},
  "huoqu_280":{},
  "huoqu_281":{},
  "huoqu_282":{},
  "huoqu_283":{},
  "huoqu_284":{},
  "huoqu_285":{},
  "huoqu_286":{},
  "huoqu_287":{},
  "huoqu_288":{},
  "huoqu_289":{},
  "huoqu_290":{},
  "huoqu_291":{},
  "huoqu_292":{},
  "huoqu_293":{},
  "huoqu_294":{},
  "huoqu_295":{},
  "huoqu_296":{},
  "huoqu_297":{},
  "huoqu_298":{},
  "huoqu_299":{},
  "huoqu_300":{},
  "huoqu_301":{},
  "huoqu_302":{},
  "huoqu_303":{},
  "huoqu_304":{},
  "huoqu_305":{},
  "huoqu_306":{},
  "huoqu_307":{},
  "huoqu_308":{},
  "huoqu_309":{},
  "huoqu_310":{},
  "huoqu_311":{},
  "huoqu_312":{},
  "huoqu_313":{},
  "huoqu_314":{},
  "huoqu_315":{},
  "huoqu_316":{},
  "huoqu_317":{},
  "huoqu_318":{},
  "huoqu_319":{},
  "huoqu_320":{},
  "huoqu_321":{},
  "huoqu_322":{},
  "huoqu_323":{},
  "huoqu_324":{},
  "huoqu_325":{},
  "huoqu_326":{},
  "huoqu_327":{},
  "huoqu_328":{},
  "huoqu_329":{},
  "huoqu_330":{},
  "huoqu_331":{},
  "huoqu_332":{},
  "huoqu_333":{},
  "huoqu_334":{},
  "huoqu_335":{},
  "huoqu_336":{},
  "huoqu_337":{},
  "huoqu_338":{},
  "huoqu_339":{},
  "huoqu_340":{},
  "huoqu_341":{},
  "huoqu_342":{},
  "huoqu_343":{},
  "huoqu_344":{},
  "huoqu_345":{},
  "huoqu_346":{},
  "huoqu_347":{},
  "huoqu_348":{},
  "huoqu_349":{},
  "huoqu_350":{},
  "huoqu_351":{},
  "huoqu_352":{},
  "huoqu_353":{},
  "huoqu_354":{},
  "huoqu_355":{},
  "huoqu_356":{},
  "huoqu_357":{},
  "huoqu_358":{},
  "huoqu_359":{},
  "huoqu_360":{},
  "huoqu_361":{},
  "huoqu_362":{},
  "huoqu_363":{},
  "huoqu_364":{},
  "huoqu_365":{},
  "huoqu_366":{},
  "huoqu_367":{},
  "huoqu_368":{},
  "huoqu_369":{},
  "huoqu_370":{},
  "huoqu_371":{},
  "huoqu_372":{},
  "huoqu_373":{},
  "huoqu_374":{},
  "huoqu_375":{},
  "huoqu_376":{},
  "huoqu_377":{},
  "huoqu_378":{},
  "huoqu_379":{},
  "huoqu_380":{},
  "huoqu_381":{},
  "huoqu_382":{},
  "huoqu_383":{},
  "huoqu_384":{},
  "huoqu_385":{},
  "huoqu_386":{},
  "huoqu_387":{},
  "huoqu_388":{},
  "huoqu_389":{},
  "huoqu_390":{},
  "huoqu_391":{},
  "huoqu_392":{},
  "huoqu_393":{},
  "huoqu_394":{},
  "huoqu_395":{},
  "huoqu_396":{},
  "huoqu_397":{},
  "huoqu_398":{},
  "huoqu_399":{},
  "huoqu_400":{},
  "huoqu_401":{},
  "huoqu_402":{},
  "huoqu_403":{},
  "huoqu_404":{},
  "huoqu_405":{},
  "huoqu_406":{},
  "huoqu_407":{},
  "huoqu_408":{},
  "huoqu_409":{},
  "huoqu_410":{},
  "huoqu_411":{},
  "huoqu_412":{},
  "huoqu_413":{},
  "huoqu_414":{},
  "huoqu_415":{},
  "huoqu_416":{},
  "huoqu_417":{},
  "huoqu_418":{},
  "huoqu_419":{},
  "huoqu_420":{},
  "huoqu_421":{},
  "huoqu_422":{},
  "huoqu_423":{},
  "huoqu_424":{},
  "huoqu_425":{},
  "huoqu_426":{},
  "huoqu_427":{},
  "huoqu_428":{},
  "huoqu_429":{},
  "huoqu_430":{},
  "huoqu_431":{},
  "huoqu_432":{},
  "huoqu_433":{},
  "huoqu_434":{},
  "huoqu_435":{},
  "huoqu_436":{},
  "huoqu_437":{},
  "huoqu_438":{},
  "huoqu_439":{},
  "huoqu_440":{},
  "huoqu_441":{},
  "huoqu_442":{},
  "huoqu_443":{},
  "huoqu_444":{},
  "huoqu_445":{},
  "huoqu_446":{},
  "huoqu_447":{},
  "huoqu_448":{},
  "huoqu_449":{},
  "huoqu_450":{},
  "huoqu_451":{},
  "huoqu_452":{},
  "huoqu_453":{},
  "huoqu_454":{},
  "huoqu_455":{},
  "huoqu_456":{},
  "huoqu_457":{},
  "huoqu_458":{},
  "huoqu_459":{},
  "huoqu_460":{},
  "huoqu_461":{},
  "huoqu_462":{},
  "huoqu_463":{},
  "huoqu_464":{},
  "huoqu_465":{},
  "huoqu_466":{},
  "huoqu_467":{},
  "huoqu_468":{},
  "huoqu_469":{},
  "huoqu_470":{},
  "huoqu_471":{},
  "huoqu_472":{},
  "huoqu_473":{},
  "huoqu_474":{},
  "huoqu_475":{},
  "huoqu_476":{},
  "huoqu_477":{},
  "huoqu_478":{},
  "huoqu_479":{},
  "huoqu_480":{},
  "huoqu_481":{},
  "huoqu_482":{"user_email": "1102055693@qq.com","user_pass": "wu123456"}
}




